configurablejson/__about__.py
configurablejson/__init__.py
configurablejson/_internals.py
configurablejson/encode.py
configurablejson/py.typed
configurable_json-1.1.0.dist-info/METADATA
configurable_json-1.1.0.dist-info/WHEEL
configurable_json-1.1.0.dist-info/RECORD
