Metadata-Version: 2.1
Name: Configurable-JSON
Version: 1.1.0
Summary: Easily Extend the JSON Encoder with Custom Rules
Project-URL: Documentation, https://github.com/trialandsuccess/configurablejson#readme
Project-URL: Issues, https://github.com/trialandsuccess/configurablejson/issues
Project-URL: Source, https://github.com/trialandsuccess/configurablejson
Author-email: Robin van der Noord <contact@trialandsuccess.nl>
License-Expression: MIT
Classifier: Development Status :: 4 - Beta
Classifier: Programming Language :: Python
Classifier: Programming Language :: Python :: 3.10
Classifier: Programming Language :: Python :: 3.11
Classifier: Programming Language :: Python :: 3.12
Classifier: Programming Language :: Python :: Implementation :: CPython
Classifier: Programming Language :: Python :: Implementation :: PyPy
Requires-Python: >=3.10
Provides-Extra: dev
Requires-Dist: hatch; extra == 'dev'
Requires-Dist: su6[all]; extra == 'dev'
